<?xml version="1.0" encoding="utf-8"?>
<TOOL_MENU_CFG>
  <MENU_ITEM NAME="SPREADSHEET_VIEW" TYPE="TOOL">
    <LABEL>Spreadsheet View</LABEL>
  </MENU_ITEM>
  <MENU_ITEM NAME="PACKAGE_VIEW" TYPE="TOOL">
    <LABEL>Package View</LABEL>
  </MENU_ITEM>
  <MENU_ITEM NAME="DEVICE_VIEW" TYPE="TOOL">
    <LABEL>Device View</LABEL>
  </MENU_ITEM>  
  <MENU_ITEM NAME="SCHEMATIC_VIEW" TYPE="TOOL">
    <LABEL>Netlist Analyzer</LABEL>
  </MENU_ITEM>
  <MENU_ITEM NAME="NETLIST_VIEW" TYPE="TOOL">
    <LABEL>Netlist View</LABEL>
  </MENU_ITEM>
  <MENU_ITEM NAME="NCD_VIEW" TYPE="TOOL">
    <LABEL>NCD View</LABEL>
  </MENU_ITEM>
  <MENU_ITEM TYPE="SEPARATOR" />
  <MENU_ITEM NAME="IPEXPRESS" TYPE="TOOL">
    <LABEL>IPexpress View</LABEL>
  </MENU_ITEM>
  <MENU_ITEM NAME="SBEXPRESS" TYPE="TOOL">
    <LABEL>System Builder Planner</LABEL>
  </MENU_ITEM>
  <MENU_ITEM TYPE="SEPARATOR" />
  <MENU_ITEM NAME="RVL_INSERTOR" TYPE="TOOL">
    <LABEL>Reveal Inserter</LABEL>
  </MENU_ITEM>
  <MENU_ITEM NAME="RVL_ANALYZER" TYPE="TOOL">
    <LABEL>Reveal Analyzer</LABEL>
  </MENU_ITEM>
  <MENU_ITEM TYPE="SEPARATOR" />
  <MENU_ITEM NAME="FLOORPLANNER" TYPE="TOOL">
    <LABEL>Floorplan View</LABEL>
  </MENU_ITEM>
  <MENU_ITEM NAME="PHYSICAL_VIEW" TYPE="TOOL">
    <LABEL>Physical View</LABEL>
  </MENU_ITEM>
  <MENU_ITEM TYPE="SEPARATOR" />
  <MENU_ITEM NAME="TIMING_ANALYZOR" TYPE="TOOL">
    <LABEL>Timing Analysis View</LABEL>
  </MENU_ITEM>
  <MENU_ITEM NAME="POWER_CALC" TYPE="TOOL">
    <LABEL>Power Calculator</LABEL>
  </MENU_ITEM>
  <MENU_ITEM NAME="NCD_EDITOR" TYPE="TOOL">
    <LABEL>ECO Editor</LABEL>
  </MENU_ITEM>
  <MENU_ITEM NAME="PROGRAMMER" TYPE="TOOL">
    <LABEL>Programmer</LABEL>
  </MENU_ITEM>
  <MENU_ITEM TYPE="SEPARATOR" />
  <MENU_ITEM NAME="SEI_EDITOR" TYPE="TOOL">
    <LABEL>SEI Editor</LABEL>
  </MENU_ITEM>
  <MENU_ITEM TYPE="SEPARATOR" />
  <MENU_ITEM NAME="PRT_MANAGER" TYPE="TOOL">
    <LABEL>Partition Manager</LABEL>
  </MENU_ITEM>
    <MENU_ITEM TYPE="SEPARATOR" />
  <MENU_ITEM NAME="PSBCONTROL_VIEW" TYPE="TOOL">
    <LABEL>Platform Designer</LABEL>
  </MENU_ITEM>
  <MENU_ITEM TYPE="SEPARATOR" />
  <MENU_ITEM NAME="Synplify Pro for Lattice" PROGRAM="launch_synplify_prj" ICON="$S/synplify.png" TYPE="CMD" CONDITION="project">
    <LABEL>"Opens Synplify Pro for Lattice GUI tool"</LABEL>
    <PARAMETER>%IM</PARAMETER>
  </MENU_ITEM>
  <MENU_ITEM NAME="Active-HDL Lattice Edition" PROGRAM="%ACTIVEHDL_PATH%/bin/avhdl" TYPE="EXE" CONDITION="project">
    <LABEL>"Opens Active-HDL Lattice Edition GUI tool"</LABEL>
  </MENU_ITEM>


</TOOL_MENU_CFG>
