<BrickEntry>
  <IsModule>1</IsModule>
  <IsProgrammable>1</IsProgrammable>
  <VrefKnown>0.700000000000000</VrefKnown>
  <VoutOpen0>0.752500000000000</VoutOpen0>
  <VoutTrimmed0>0.000000000000000</VoutTrimmed0>
  <VoutOpen1>0.752500000000000</VoutOpen1>
  <VoutTrimmed1>1.200000000000000</VoutTrimmed1>
  <Rtgnd1>41973</Rtgnd1>
  <VoutOpen2>0.752500000000000</VoutOpen2>
  <VoutTrimmed2>3.300000000000000</VoutTrimmed2>
  <Rtgnd2>3160</Rtgnd2>
  <VoutOpen3>0.000000000000000</VoutOpen3>
  <VoutTrimmed3>0.000000000000000</VoutTrimmed3>
  <RtVout3>0</RtVout3>
  <Comments>
<![CDATA[
]]>
</Comments>
</BrickEntry>

