<?xml version="1.0" encoding="UTF-8"?>
<messageFile name="o5gtw" fid="7001" alias="o5gtw" vendor="Lattice Semiconductor Corporation" stamp="Date and Time">
  <description text="this message file contains message for [name] package"/>
  <!-- owner of this message file -->
  <owner text="owner" />
  <messages>

	<msg uid="1001" type="Error" text="For $$s pcmtype $$d does not match $$d for &lt;$$s&gt;."/>
	<msg uid="1002" type="Warning" level="2" text="PCM: $$s mclk has no preference\n"/>
	<msg uid="1003" type="Warning" level="2" text="PCM: $$s mclk pin not connected\n"/>
	<msg uid="1004" type="Warning" level="2" text="PCM: $$s nclk has no preference\n"/>
	<msg uid="1005" type="Warning" level="2" text="PCM: $$s nclk pin not connected\n"/>
	<msg uid="1006" type="Warning" level="2" text="Frequency is not defined on $$s pin $$s\n"/>
	<msg uid="1007" type="Warning" level="2" text="Cannot find feedback frequency for $$s\n"/>
	<msg uid="1008" type="Warning" level="2" text="Input and feedback clock frequencies do not match their divider settings for $$s. If you desire to change the PLL frequency settings, you may do so by regenerating your PLL module.\n"/>
	<msg uid="1009" type="Warning" level="2" text="Bypassed output clock $$s frequency does not match input clock for $$s. If you desire to change the PLL frequency settings, you may do so by regenerating your PLL module.\n"/>
	<msg uid="1010" type="Warning" level="2" text="The Preference FREQUENCY NET at signal $$s ($$s) or signal $$s ($$s) do not match their divider settings for $$s. If you desire to change the PLL frequency settings, you may do so by regenerating your PLL module.\n"/>
	<msg uid="1011" type="Warning" level="2" text="The Preference FREQUENCY NET at pin $$s or pin $$s do not match their divider settings for $$s. If you desire to change the PLL frequency settings, you may do so by regenerating your PLL module.\n"/>

	</messages>
</messageFile>
