<?xml version="1.0" encoding="UTF-8"?>
<messageFile name="s5pncdesign" fid="6712" alias="s5pncdesign" vendor="Lattice Semiconductor Corporation" stamp="Date and Time">
  <description text="this message file contains message for [name] package"/>
  <!-- owner of this message file -->
  <owner text="owner" />
  <messages>

	<msg uid="1001" type="Warning" level="2" text="Missing input for DCC '$$s'.\n"/>
	<msg uid="1002" type="Warning" level="2" text="DCC CLKI '$$s' driven by DCS '$$s' takes additional PCLK spine/CIB.\n"/>
	<msg uid="1003" type="Warning" level="2" text="DCC '$$s' has dangling output.\n"/>
	<msg uid="1004" type="Warning" level="2" text="(User pref. primary clock) Signal &quot;$$s&quot; specified as quadrant clocks does not drive any CLK/CR/LSR inputs.\n"/>
	<msg uid="1005" type="Warning" level="2" text="(User pref or system clock) Signal &quot;$$s&quot; is not selected as a quadrant clock in quadrant $$s due to clock resource constraint.\n"/>
	<msg uid="1006" type="Warning" level="2" text="(User pref or system clock) Signal &quot;$$s&quot; is not selected as a quadrant clock in quadrant $$s; maximum of $$d signals are already selected.\n"/>
	<msg uid="1007" type="Error" text="Clock assignment failed due to high utilization (#SIGNAL=$$d).\n"/>
	<msg uid="1008" type="Error" text="No DQS / DQ pads associated with this DQSBUF site &quot;$$s&quot;."/>
	<msg uid="1009" type="Status" text="## $$s.$$s =&gt; $$s.$$s\n"/>
	<msg uid="1010" type="Error" text="The DDRDEL input of DQSBUF comp &quot;$$s&quot; is driven by &quot;$$s&quot;.$$s, which is illegal."/>
	<msg uid="1011" type="Error" text="The DDRDEL input of DLLDEL comp &quot;$$s&quot; is driven by &quot;$$s&quot;.$$s, which is illegal."/>
	<msg uid="1012" type="Error" text="Signal &quot;$$s&quot; has no driver comp."/>
	<msg uid="1013" type="Error" text="Invalid CRU configuration found: The output signal &quot;$$s&quot; of CRU comp &quot;$$s&quot; drives $$d IOLOGIC comps, but should drive 1 only. Correct your design."/>
	<msg uid="1014" type="Error" text="Invalid device capture for DSP slice $$s, grid ($$d,$$d)\n"/>
	<msg uid="1015" type="Error" text="(SLICE_$$d): comp '$$s': Loop found in forming DSP shiftchain SLICE_$$d.\n"/>
	<msg uid="1016" type="Error" text="DSP comps '$$s' and '$$s' in shiftchain cannot be different types.\n"/>
	<msg uid="1017" type="Error" text="DSP comp '$$s' in chain cannot have grounded SRI pin.\n"/>
	<msg uid="1018" type="Error" text="The length of DSP chain (comp '$$s') exceeds device limitation $$d.\n"/>
	<msg uid="1019" type="Error" text="Unable to identify DSP cluster for comp '$$s'.\n"/>
	<msg uid="1020" type="Error" text="DSP $$s driving two ALU24 comps $$s and $$s.\n"/>
	<msg uid="1021" type="Error" text="DSP $$s driving two ALU54 comps $$s and $$s.\n"/>
	<msg uid="1022" type="Error" text="DSP $$s is driven by two distinct PREADD9 comps $$s and $$s\n"/>
	<msg uid="1023" type="Error" text="DSP $$s is driven by two distinct PREADD18 comps $$s and $$s\n"/>
	<msg uid="1024" type="Error" text="DSP MULT9 '$$s' cannot be driven by PREADD18 comp '$$s'.\n"/>
	<msg uid="1025" type="Error" text="DSP MULT18 '$$s' cannot be driven by PREADD9 comp '$$s'.\n"/>
	<msg uid="1026" type="Error" text="DSP MULT '$$s' cannot be driven by two PRADD comps '$$s' and '$$s'.\n"/>
	<msg uid="1027" type="Error" text="PRADD $$s does not have a corresponding MULT.\n"/>
	<msg uid="1028" type="Error" text="DSP $$s's (M)A inputs driven by multiple multipliers -- $$s, $$s and $$s.\n"/>
	<msg uid="1029" type="Error" text="DSP $$s's (M)A inputs driven by two different MULT9 comps $$s and $$s.\n"/>
	<msg uid="1030" type="Error" text="DSP $$s's (M)A inputs driven by two different MULT18 comps $$s and $$s.\n"/>
	<msg uid="1031" type="Error" text="DSP $$s's (M)B inputs driven by multiple multipliers -- $$s, $$s and $$s.\n"/>
	<msg uid="1032" type="Error" text="DSP $$s's (M)B inputs driven by two different MULT9 comps $$s and $$s.\n"/>
	<msg uid="1033" type="Error" text="DSP $$s's (M)B inputs driven by two different MULT18 comps $$s and $$s.\n"/>
	<msg uid="1034" type="Error" text="DSP $$s's CIN driven by two different ALU comps $$s and $$s.\n"/>
	<msg uid="1035" type="Error" text="DSP $$s's output R driving two different ALU comps $$s and $$s.\n"/>
	<msg uid="1036" type="Error" text="DSP $$s's CINs must be driven by a different ALU.\n"/>
	<msg uid="1037" type="Error" text="DSP comp $$s driving more than one comp through SRO pin.\n"/>
	<msg uid="1038" type="Error" text="DSP comp $$s and $$s are incompatible and cannot be in one shiftchain.\n"/>
	<msg uid="1039" type="Error" text="Loop found for PRADD $$s.\n"/>
	<msg uid="1040" type="Warning" level="2" text="Driver $$s of PRADD $$s's SRIA has different DSP type.\n"/>
	<msg uid="1041" type="Warning" level="2" text="More than one DSP type driver found for PRADD $$s.\n"/>
	<msg uid="1042" type="Warning" level="2" text="Load $$s of PRADD $$s's SROB has different DSP type.\n"/>
	<msg uid="1043" type="Warning" level="2" text="Driver $$s of PRADD $$s's SRIB has different DSP type.\n"/>
	<msg uid="1044" type="Warning" level="2" text="Load $$s of PRADD $$s's SROA has different DSP type.\n"/>
	<msg uid="1045" type="Error" text="Unable to find ECLKSYNC site &quot;$$s&quot; for ECLK$$d in I/O bank $$d."/>
	<msg uid="1046" type="Error" text="[Capture] Unable to find ECLKSYNC site &quot;$$s&quot; for BANK$$d_ECLK$$d."/>
	<msg uid="1047" type="Status" text="&gt;&gt;&gt; $$s.$$s =&gt; $$s.$$s\n"/>
	<msg uid="1048" type="Status" text="&gt;&gt;&gt; $$s.$$s =&gt; $$s\n"/>
	<msg uid="1049" type="Status" text="ECLK: DLLDEL site &quot;$$s&quot; ==&gt; $$s.\n"/>
	<msg uid="1050" type="Error" text="ECLK signal &quot;$$s&quot; drives $$d CLKDIV comps.  One ECLK signal should drive one CLKDIV comp only per architecture."/>
	<msg uid="1051" type="Status" text="&gt;&gt;&gt; &quot;$$s.$$s&quot; =&gt; &quot;$$s.$$s&quot;."/>
	<msg uid="1052" type="Warning" level="2" text="Module's region is not set correctly. The default region, i.e. entire device, will be used."/>
	<msg uid="1053" type="Warning" level="2" text="The module's left boundary is defined outside of device boundary.\n"/>
	<msg uid="1054" type="Warning" level="2" text="The module's right boundary is defined outside of device boundary.\n"/>
	<msg uid="1055" type="Warning" level="2" text="The module's bottom boundary is defined outside of device boundary.\n"/>
	<msg uid="1056" type="Warning" level="2" text="The module's top boundary is defined outside of device boundary.\n"/>
	<msg uid="1057" type="Error" text="Incorrect netlist: the IOLTO output of IOLOGIC comp &quot;$$s&quot; drives a non-PIO comp &quot;$$s&quot;."/>
	<msg uid="1058" type="Error" text="The $$s output of IOLOGIC comp &quot;$$s&quot; has incorrect connections to comp &quot;$$s&quot; and &quot;$$s&quot;."/>
	<msg uid="1059" type="Error" text="The $$s input of IOLOGIC comp &quot;$$s&quot; has incorrect connections to comp &quot;$$s&quot; and &quot;$$s&quot;."/>
	<msg uid="1060" type="Error" text="The paired comp &quot;$$s&quot; of IOLOGIC comp &quot;$$s&quot; is not a PIO."/>
	<msg uid="1061" type="Error" text="Incorrect netlist: the $$s input of PIO comp &quot;$$s&quot; is driven by a non-IOLOGIC comp &quot;$$s&quot;."/>
	<msg uid="1062" type="Error" text="The $$s input of PIO comp &quot;$$s&quot; has incorrect connections to comp &quot;$$s&quot; and &quot;$$s&quot;."/>
	<msg uid="1063" type="Error" text="The paired comp &quot;$$s&quot; for PIO comp &quot;$$s&quot; is not an IOLOGIC."/>
	<msg uid="1064" type="Error" text="This device does not have a valid PKG file."/>
	<msg uid="1065" type="Error" text="Could not find PAD_TYPE or PAD_GID or FNC column in the PKG file."/>
	<msg uid="1066" type="Warning" level="2" text="PKG file: PAD_TYPE entry is not a string."/>
	<msg uid="1067" type="Warning" level="2" text="PKG file: PAD_GID entry is not a number."/>
	<msg uid="1068" type="Warning" level="2" text="PKG file: FNC entry is not a string."/>
	<msg uid="1069" type="Status" text="&gt;&gt;&gt; bank $$d: &quot;$$s.$$s&quot; =&gt; &quot;$$s.$$s&quot;."/>
	<msg uid="1070" type="Error" text="The proposed VREF input pin for I/O bank $$d is &quot;$$s / $$s&quot;; however, this pin is in a different I/O bank $$d.  It will not be used as a VREF pin for bank $$d."/>
	<msg uid="1071" type="Error" text="The proposed VREF pin &quot;$$s / $$s&quot; for I/O bank $$d is not a valid VREF for that bank. It will not be used as a VREF pin for bank $$d."/>
	<msg uid="1072" type="Warning" level="2" text="VREF &quot;$$s&quot; it not used in this design.  It will be ignored."/>
	<msg uid="1073" type="Error" text="VREF &quot;$$s&quot; does not require an external VREF input pin."/>
	<msg uid="1074" type="Error" text="PIO &quot;$$s / $$s&quot; is to be used as a VREF input pin, in the meanwhile it is locked for another PIO comp.;  therefore, it cannot be used as a VREF pin."/>
	<msg uid="1075" type="Error" text="PIO site &quot;$$s / $$s&quot; is not bonded out, it cannot be used as a VREF input pin."/>
	<msg uid="1076" type="Error" text="PIO site &quot;$$s / $$s&quot; is prohibited, it cannot be used as a VREF input pin."/>
	<msg uid="1077" type="Error" text="PIO site &quot;$$s / $$s&quot; is a SysConfig pin, it cannot be used as a VREF input pin."/>
	<msg uid="1078" type="Warning" level="2" text="Multiple Vref1 drivers (&quot;$$s/$$s&quot; and &quot;$$s/$$s&quot;) for the same VREF in I/O bank $$d.  The later will be ignored."/>
	<msg uid="1079" type="Error" text="The VREF1 pin of I/O bank &quot;$$d&quot; has already been assigned to PIO site &quot;$$s/$$s&quot;, it cannot be changed to &quot;$$s/$$s&quot;."/>
	<msg uid="1080" type="Error" text="The VREF1 of I/O bank &quot;$$d&quot; has already been set to &quot;$$s&quot;, it cannot be changed to &quot;$$s&quot;."/>
	<msg uid="1081" type="Error" text="&gt;&gt; [2] S5P_PIO_BANK::update() -- Bank $$d: Vref1=$$s, vs. the internal generated VREF to be set=$$s."/>
	<msg uid="1082" type="Error" text="&gt;&gt; [3] S5P_PIO_BANK::update() -- Bank $$d: Vref1/2=($$s, $$s) vs. the VREF to be set=$$s; the availability of VREF sites: ($$s, $$s)."/>
	<msg uid="1083" type="Error" text="S5P_PIO_BANK::place_update_vref(): Inconsistent internal VREF state found -- PIO comp &quot;$$s&quot;: VREF=$$s, bank $$d: Vref1=$$s."/>
	<msg uid="1084" type="Error" text="I/O bank $$d does not support VREF input."/>
	<msg uid="1085" type="Error" text="PIO comp &quot;$$s&quot; requires VREF=$$s, but bank $$d has Vref1/2=($$s, $$s)."/>
	<msg uid="1086" type="Error" text="PIO como &quot;$$s&quot; has to use the VREF1 rail driven by the internal VREF generator, but currently it is using VREF2."/>
	<msg uid="1087" type="Error" text="S5P_PIO_BANK::unplace_update_diffdrive(): Inconsistent internal DIFFDRIVE state found -- PIO comp &quot;$$s&quot;: DIFFDRIVE=$$s, bank $$d: DIFFDRIVE=$$s."/>
	<msg uid="1088" type="Error" text="S5P_PIO_BANK::unplace_update_vcm(): Inconsistent internal VCM state found -- PIO comp &quot;$$s&quot;: VCM=$$s, bank $$d: VCM=$$s."/>
	<msg uid="1089" type="Error" text="PIO comp &quot;$$s&quot; is a MIPI input and it has been placed on PIO site &quot;$$s/$$s&quot; (a $$c pad), but its paired PIO comp &quot;$$s&quot; (a MIPI input) is not placed yet."/>
	<msg uid="1090" type="Error" text="PIO comp &quot;$$s&quot; is a MIPI input and it requires a $$c pad, but it has been incorrectly placed on PIO site &quot;$$s/$$s&quot;.  It should be placed on &quot;$$s/$$s&quot; (a $$c pad), because its paired MIPI comp &quot;$$s&quot; (requires a $$c pad) has been placed on &quot;$$s/$$s&quot; (which is a $$c pad)."/>
	<msg uid="1091" type="Error" text="PIO comp &quot;$$s&quot; is a MIPI input and it has been placed on PIO site &quot;$$s/$$s&quot; (a $$c pad), but the paired PIO site &quot;$$s/$$s&quot; (a $$c pad) is left empty."/>
	<msg uid="1092" type="Error" text="PIO comp &quot;$$s&quot; is a MIPI input and it requires a $$c pad, so it cannot be placed on PIO site &quot;$$s/$$s&quot; (a $$c pad), because this PIO site has been $$s."/>
	<msg uid="1093" type="Error" text="PIO comp &quot;$$s&quot; is MIPI input and it requires a $$c pad, but it has been placed on PIO site &quot;$$s/$$s&quot;, which is a $$c PAD."/>
	<msg uid="1094" type="Error" text="PIO comp &quot;$$s&quot; has DIFFDRIVE=$$s; however, bank $$d has DIFFDRIVE=$$s."/>
	<msg uid="1095" type="Error" text="PIO comp &quot;$$s&quot; has VCM=$$s; however, bank $$d has VCM=$$s."/>
	<msg uid="1096" type="Error" text="PIO site &quot;$$s/$$s&quot; is a required VREF pin, it will not be used."/>
	<msg uid="1097" type="Error" text="I/O bank $$d (DIFFDRIVE=&quot;$$s&quot;): cannot change its DIFFDRIVE to &quot;$$s&quot;.  Make sure that the DIFFDRIVE requirements of locked PIO comps to the same I/O bank are compatible with each other."/>
	<msg uid="1098" type="Error" text="I/O bank $$d (VCM=&quot;$$s&quot;): cannot change its VCM to &quot;$$s&quot;.  Make sure that the VCM requirements of locked PIO comps to the same I/O bank are compatible with each other."/>
	<msg uid="1099" type="Error" text="I/O bank $$d has an internal VREF on its VREF2: Vref2=$$s."/>
	<msg uid="1100" type="Error" text="I/O bank $$d, Vref1/2=($$s, $$s): incompatible VREF &quot;$$s&quot; cannot be assigned to this bank."/>
	<msg uid="1101" type="Error" text="I/O banking group 0x$$x has 2 internal Vrefs: Vref1/2=($$s, $$s)."/>
	<msg uid="1102" type="Error" text="I/O banking group 0x$$x, Vref1/2=($$s, $$s): incompatible VREF &quot;$$s&quot; cannot be assigned to this group."/>
	<msg uid="1103" type="Error" text="Sapphire :: PIO site &quot;$$s / $$s&quot;: IOL site &quot;$$s&quot; has unknown type."/>
	<msg uid="1104" type="Error" text="PIO comp &quot;$$s&quot;: IOL comp &quot;$$s&quot; has unknown type."/>
	<msg uid="1105" type="Warning" level="2" text="No sites connect to site &quot;$$s&quot;, pin &quot;$$s&quot;."/>
	<msg uid="1106" type="Status" text="&gt;&gt;&gt; [$$s] PLL CLKI input PIO &quot;$$s/$$s&quot; [CFG: $$s]."/>
	<msg uid="1107" type="Status" text="&gt;&gt;&gt; [??] PLL CLKI input PIO &quot;$$s/$$s&quot;."/>
	<msg uid="1108" type="Status" text="&gt;&gt;&gt;   PLL.CLKFB - &quot;$$s/$$s&quot;.$$s =&gt; &quot;$$s.$$s\."/>
	<msg uid="1109" type="Status" text="&gt;&gt;&gt; [$$s] PLL CLKFB input PIO &quot;$$s/$$s&quot; [CFG: $$s]."/>
	<msg uid="1110" type="Status" text="&gt;&gt;&gt; [??] PLL CLKFB input PIO &quot;$$s/$$s&quot;."/>
	<msg uid="1111" type="Warning" level="2" text="No nodes connect to node &quot;$$s&quot;."/>
	<msg uid="1112" type="Warning" level="2" text="No sites connect to node &quot;$$s&quot;."/>
	<msg uid="1113" type="Status" text="&gt;&gt;&gt;   node &quot;$$s&quot; =&gt; &quot;$$s.$$s\."/>
	<msg uid="1114" type="Warning" text="Unable to assign signal '$$s' to clock tree due to resource constraint. $$s device allows only $$d primary clocks.\n"/>
	<msg uid="1115" type="Error" text="Unable to assign signal '$$s' to clock tree due to resource constraint. $$s device allows only $$d primary clocks.\n"/>
	<msg uid="1116" type="Error" text="Clock '$$s' has illegal source from DLLDEL $$s's '$$s' output (only 'Z' pin is legal).\n"/>
        <msg uid="1117" type="Error" text="Illegal connection in DSP cluster containing comp '$$s'. Please consult the Lattice DSP Usage Guide or Lattice technical support for the appropriate constraints when using DSP components.\n"/>

	</messages>
</messageFile>
